{
  "persons": [
    {
      "name": "Arto Hellas",
      "number": "111-1111 1111",
      "id": "1"
    },
    {
      "name": "Ada Lovelace",
      "number": "39-44-5323523",
      "id": "2"
    },
    {
      "name": "Dan Abramov",
      "number": "12-43-234345",
      "id": "3"
    },
    {
      "name": "hola",
      "number": "23415 4215 2415",
      "id": "f22d"
    },
    {
      "id": "2f18",
      "name": "sdfsdf",
      "number": "f1342343"
    },
    {
      "id": "7415",
      "name": "May Popi",
      "number": "789 321 456"
    }
  ]
}